dateroll/__init__.py
dateroll/__main__.py
dateroll/cli.py
dateroll/pretty.py
dateroll/settings.py
dateroll/tblfmt.py
dateroll/utils.py
dateroll/calendars/__init__.py
dateroll/calendars/__main__.py
dateroll/calendars/calendarmath.py
dateroll/calendars/calendars.py
dateroll/calendars/sampledata.py
dateroll/date/__init__.py
dateroll/date/__main__.py
dateroll/date/date.py
dateroll/ddh/__init__.py
dateroll/ddh/__main__.py
dateroll/ddh/ddh.py
dateroll/duration/__init__.py
dateroll/duration/__main__.py
dateroll/duration/duration.py
dateroll/parser/__init__.py
dateroll/parser/__main__.py
dateroll/parser/parser.py
dateroll/parser/parsers.py
dateroll/parser/patterns.py
dateroll/sampledata/ALL.csv
dateroll/sampledata/BR.csv
dateroll/sampledata/ECB.csv
dateroll/sampledata/FED.csv
dateroll/sampledata/LN.csv
dateroll/sampledata/NY.csv
dateroll/sampledata/WE.csv
dateroll/schedule/__init__.py
dateroll/schedule/__main__.py
dateroll/schedule/schedule.py
dateroll-0.2.13.dist-info/licenses/LICENSE
dateroll-0.2.13.dist-info/METADATA
dateroll-0.2.13.dist-info/WHEEL
dateroll-0.2.13.dist-info/entry_points.txt
dateroll-0.2.13.dist-info/top_level.txt
dateroll-0.2.13.dist-info/RECORD
